brocolli/__init__.py
brocolli/converter/__init__.py
brocolli/converter/common_utils.py
brocolli/converter/onnx_utils.py
brocolli/converter/optimizer.py
brocolli/converter/pytorch_caffe_parser.py
brocolli/converter/pytorch_graph.py
brocolli/converter/pytorch_onnx_parser.py
brocolli/converter/onnx_layers/__init__.py
brocolli/converter/onnx_layers/abs_func.py
brocolli/converter/onnx_layers/add_layer.py
brocolli/converter/onnx_layers/avgpool_func.py
brocolli/converter/onnx_layers/avgpool_layer.py
brocolli/converter/onnx_layers/baddbmm_func.py
brocolli/converter/onnx_layers/base_layer.py
brocolli/converter/onnx_layers/batchnorm_layer.py
brocolli/converter/onnx_layers/bnll_layer.py
brocolli/converter/onnx_layers/cast_layer.py
brocolli/converter/onnx_layers/celu_func.py
brocolli/converter/onnx_layers/chunk_func.py
brocolli/converter/onnx_layers/clip_func.py
brocolli/converter/onnx_layers/concat_func.py
brocolli/converter/onnx_layers/conv_func.py
brocolli/converter/onnx_layers/conv_layer.py
brocolli/converter/onnx_layers/conv_transpose_layer.py
brocolli/converter/onnx_layers/cosine_func.py
brocolli/converter/onnx_layers/custom_layer.py
brocolli/converter/onnx_layers/div_func.py
brocolli/converter/onnx_layers/dropout_layer.py
brocolli/converter/onnx_layers/elu_func.py
brocolli/converter/onnx_layers/elu_layer.py
brocolli/converter/onnx_layers/embedding_layer.py
brocolli/converter/onnx_layers/exp_func.py
brocolli/converter/onnx_layers/exp_layer.py
brocolli/converter/onnx_layers/flatten_func.py
brocolli/converter/onnx_layers/flatten_layer.py
brocolli/converter/onnx_layers/gelu_layer.py
brocolli/converter/onnx_layers/gemm_func.py
brocolli/converter/onnx_layers/gemm_layer.py
brocolli/converter/onnx_layers/getattr_func.py
brocolli/converter/onnx_layers/getitem_func.py
brocolli/converter/onnx_layers/glu_func.py
brocolli/converter/onnx_layers/gru_layer.py
brocolli/converter/onnx_layers/hardsigmoid_func.py
brocolli/converter/onnx_layers/hardsigmoid_layer.py
brocolli-4.0.2.dist-info/LICENSE
brocolli-4.0.2.dist-info/METADATA
brocolli-4.0.2.dist-info/WHEEL
brocolli-4.0.2.dist-info/top_level.txt
brocolli-4.0.2.dist-info/RECORD
