Metadata-Version: 2.1
Name: brocolli
Version: 4.0.2
Summary: everything in pytorch
Home-page: https://github.com/inisis/brocolli
Author: desmond
Author-email: desmond.yao@buaa.edu.cn
Project-URL: Bug Tracker, https://github.com/inisis/brocolli/issues
Keywords: machine-learning,pytorch,caffe,torchfx
Classifier: Programming Language :: Python :: 3
Classifier: License :: OSI Approved :: MIT License
Classifier: Operating System :: OS Independent
Classifier: Topic :: Scientific/Engineering :: Artificial Intelligence
Requires-Python: >=3.6
License-File: LICENSE
Requires-Dist: loguru
Requires-Dist: onnx (==1.9.0)
Requires-Dist: onnxruntime (==1.8.0)
Requires-Dist: tabulate
